{"_id":"50ab844a898d651cc800001c","chief_editor_country_grade":0,"chief_editor_grade":0,"deck":"<div style=\"float:right;margin-bottom:10px;margin-left:5px;\"><a target=\"_blank\" type=\"box_count\" name=\"fb_share\" href=\"http://www.facebook.com/sharer.php?u=http://mashable.com/2012/11/19/social-media-tv-chart-11-19/&src=sp\" style=\"text-decoration: none;\"><img style=\"border:none;margin-right:5px;\" src=\"http://6.mshcdn.com/wp-content/themes/v7/img/share-buttons/fb.jpg\" align=\"right\" /></a><br />\n<a target=\"_blank\" href=\"http://twitter.com/share?url=http://mashable.com/2012/11/19/social-media-tv-chart-11-19/&amp;via=mashable\"><img style=\"border:none;margin-right:5px;\" width=\"51\" height=\"51\" src=\"http://6.mshcdn.com/wp-content/themes/v7/img/tweet.jpg\" align=\"right\"/></a></div>\n<p><a href=\"http://mashable.com/2012/11/19/social-media-tv-chart-11-19/\"><img src=\"http://6.mshcdn.com/wp-content/uploads/2012/03/social-tv-600.jpg\" style=\"max-width:575px;height:auto;margin:0 auto 10px auto;display:block;\" /></a>It should come as no surprise to anyone who follows the social TV rankings that <a href=\"http://mashable.com/follow/topics/the-x-factor/\"><em>The X Factor</em></a> has once again topped the chart this week. </p>\n<p>FOX's singing competition spurred more than 4.5 million mentions on social networks, rising 15% from last week's total as season two nears its conclusion. Season three has already been confirmed, though next year's judge lineup has not been announced. Whether or not judges <a href=\"http://www.mashable.com/follow/topics/britney-spears/\">Britney Spears</a> and <a href=\"http://www.mashable.com/follow/topics/demi-lovato/\">Demi Levato</a> will return alongside <a href=\"http://mashable.com/follow/topics/simon-cowell/\">Simon Cowell</a> and L.A. Reid remains to be seen. </p>\n<p><strong>SEE ALSO: <a href=\"http://mashable.com/2012/11/14/major-league-gaming-numbers/\">Competitive Gaming Seeing TV-Levels of Viewership in 2012</a></strong></p>\n<p><em>The X Factor</em> season two premiere <a href=\"http://mashable.com/2012/09/13/x-factor-premiere-breaks-social-tv-record/\">broke records</a> to become the most talked about premiere for a series ever back&#8230; <br /><a href=\"http://mashable.com/2012/11/19/social-media-tv-chart-11-19/\" >Continue reading...</a></p>\n<p>More About: <a href=\"http://mashable.com/tag/entertainment/\">Entertainment</a>, <a href=\"http://mashable.com/tag/social-media/\">Social Media</a>, <a href=\"http://mashable.com/tag/tv/\">TV</a>, <a href=\"http://mashable.com/tag/trendrr/\">Trendrr</a>, <a href=\"http://mashable.com/tag/infographics/\">infographics</a>, <a href=\"http://mashable.com/tag/social-tv/\">social tv</a>, <a href=\"http://mashable.com/tag/social-tv-charts/\">social tv charts</a></p>","editors_grade":0,"guid":"http://mashable.com/?p=1504339","headline":"20 TV Shows With the Most Social Buzz This Week","is_published":false,"published_on":"2012-11-19T00:00:00Z","url":"http://feeds.mashable.com/~r/Mashable/~3/4J7iTZod7Ok/"}