{"_id":"50ab8377898d651b4900008f","chief_editor_country_grade":0,"chief_editor_grade":0,"deck":null,"editors_grade":0,"guid":"http://www.nytimes.com/2012/11/20/opinion/100-75-50-years-ago.html","headline":"FROM THE INTERNATIONAL HERALD TRIBUNE; 100, 75, 50 Years Ago","is_published":false,"published_on":null,"story":"1912 Convicts Mutiny at Prison PARIS &mdash; Troops had to be called out and were compelled to make use of their rifles to quell a mutiny at Rochefort prison yesterday [Nov. 19] evening, in the course of which the chief warder and his wife were murdered by the convicts and three other persons were killed. The prisoners attacked the warders with","url":"http://www.nytimes.com/2012/11/20/opinion/100-75-50-years-ago.html"}